README.txt
setup.py
archetypes/__init__.py
archetypes.ldapstorage.egg-info/PKG-INFO
archetypes.ldapstorage.egg-info/SOURCES.txt
archetypes.ldapstorage.egg-info/dependency_links.txt
archetypes.ldapstorage.egg-info/entry_points.txt
archetypes.ldapstorage.egg-info/namespace_packages.txt
archetypes.ldapstorage.egg-info/not-zip-safe
archetypes.ldapstorage.egg-info/paster_plugins.txt
archetypes.ldapstorage.egg-info/requires.txt
archetypes.ldapstorage.egg-info/top_level.txt
archetypes/ldapstorage/__init__.py
archetypes/ldapstorage/config.py
archetypes/ldapstorage/configure.zcml
archetypes/ldapstorage/exceptions.py
archetypes/ldapstorage/log.py
archetypes/ldapstorage/storage.py
archetypes/ldapstorage/todo.txt
archetypes/ldapstorage/examples/ExampleContent.py
archetypes/ldapstorage/examples/ExampleContent2.py
archetypes/ldapstorage/examples/__init__.py
archetypes/ldapstorage/profiles/example/metadata.xml
archetypes/ldapstorage/profiles/example/types.xml
archetypes/ldapstorage/profiles/example/types/ExampleContent.xml
archetypes/ldapstorage/profiles/example/types/ExampleContent2.xml
archetypes/ldapstorage/tests/__init__.py
archetypes/ldapstorage/tests/config.py
archetypes/ldapstorage/tests/testLDAPStorage.py
archetypes/ldapstorage/tests/input/photo.png
docs/HISTORY.txt
docs/INSTALL.txt
docs/LICENSE.txt