Metadata-Version: 1.0
Name: archetypes.ldapstorage
Version: 0.1a1
Summary: LDAP Storage for Archetypes
Home-page: http://plone.org/products/archetypes.ldapstorage
Author: Ricardo Alves
Author-email: rsa@eurotux.com
License: GPL
Keywords: plone archetypes ldap storage
Platform: UNKNOWN
Classifier: Framework :: Plone
Classifier: Programming Language :: Python
Classifier: Topic :: Software Development :: Libraries :: Python Modules
